{
  "meta": {
    "theme": "elegant"
  },
  "basics": {
    "name": "Guillermo Nicolas Hamity",
    "label": "Researcher in High Energy Particle Physics",
    "email": "ghamity@pm.me",
    "phone": "0x1B59829E2",
    "image": "https://media-exp1.licdn.com/dms/image/C4D03AQFfw66UWibggA/profile-displayphoto-shrink_800_800/0/1622196034127?e=1669852800&v=beta&t=EI5Qta8OcbWC5YB6D1aCAUles-I1QzqwWFxmQdM_M48",
    "resumeqr": "https://www2.ph.ed.ac.uk/~ghamity/CVlink.png",
    "phoneqr": "https://www2.ph.ed.ac.uk/~ghamity/phonenumber.png",
    "summary": 
      "Decade+ in \\textbf{applied data analysis} with expertise in \\emph{code development and deployment, data preparation, distributed computing, machine learning, and hypothesis testing}. Currently leverage ML for stochastic modelling in sports betting markets. Previously a researcher at the \\emph{Large Hadron Collider, CERN}. Involved in leading publications and experienced in \\textbf{collaborative research} and \\textbf{supervision}, held \\textbf{leadership} roles within the 3000+ people collaboration, and am an \\textbf{efficient independent} worker and clear \\textbf{communicator}.",
    "profiles": [
      {
        "network": "Personal Website",
        "url": "https://guillermohamity.github.io/",
        "username": "guillermohamity.github.io/"
      },
      {
        "network": "LinkedIn",
        "username": "ghamity",
        "url": "https://www.linkedin.com/in/guillermo-hamity"
      },
      {
        "network": "Github",
        "username": "guillermohamity",
        "url": "https://github.com/guillermohamity"
      },
      {
        "network": "Gitlab",
        "username": "ghamity",
        "url": "https://gitlab.cern.ch/users/ghamity/activity"
      },
      {
	    "network": "orcid",
	    "username": "0000-0002-4537-0377",
	    "url": "https://orcid.org/0000-0002-4537-0377"
      },
      {
        "network": "Twitter",
        "url": "https://twitter.com/hamitynicolas",
        "username": "HamityNicolas"
      }
    ]
  },
  "education": [
    {
      "studyType": "PhD in High Energy Particle Physics",
      "institution": "The University of Sheffield (UK)",
      "startDate": "2019",
      "endDate": "2015"
    },
    {
      "studyType": "MSc in Physics",
      "institution": "Uni of Witwatersrand (ZAR)",
      "startDate": "2015",
      "endDate": "2013"
    },
    {
      "studyType": "BSc and Honours in Physics",
      "institution": "The University of Pretoria (ZAR)",
      "startDate": "2012",
      "endDate": "2008"
    }
  ],
  
"languages": [
    {
      "name": "",
      "language": "English",
      "fluency": "Native"
    },
    {
      "language": "Spanish",
      "fluency": "Native"
    },
    {"language": "Afrikaans",
    "fluency": "Conversational"
    },
    {
      "language": "French",
      "fluency": "Beginner"
    }
  ],

"publications": [
  {
    "name": "JHEP09(2018)139",
    "url": "10.1007/JHEP09(2018)139",
    "publisher": "J. High Energ. Phys. 2018, 139",
    "summary": "Search for charged Higgs bosons decaying via $H^\pm\rightarrow\tau\nu$ in the  $\tau$+jets and $\tau$+lepton final states with 36 $fb^{−1}$ of pp collision data recorded at $\sqrt{s}$ = 13 TeV with the ATLAS experiment",
    "releaseDate": "2018"

  },
  {
    "name": "PhysRevLett. 125.051801",
    "url": "10.1103/PhysRevLett.125.051801",
    "publisher": "Phys. Rev. Lett. 125, 051801",
    "summary": "Search for additional heavy Higgs Boson decaying into Two Tau Leoptons with the ATLAS Detector Using 36 fb1 of pp collisions at √s = 13 TeV with the ATLAS detector.",
    "releaseDate": "2020"
  },
  {
    "name": "PhysRevD. 101.012002",
      "url": "10.1103/PhysRevD.101.012002",
      "publisher": "Phys. Rev. D 101, 012002",
    "summary": "Combined measurements of Higgs boson production and decay using up to 80 invfb of proton–proton collision data at 13 TeV collected with the ATLAS experiment",
    "releaseDate": "2020"
  },
  {
    "name": "ATLAS-CONF-2022-034",
    "url": "https://cds.cern.ch/record/2810156",
    "summary": "Search for heavy long-lived multi-charged particles in the full Run-II $pp$ collision data at $\\sqrt{s}$ = 13 TeV using the ATLAS detector",
    "releaseDate": "2022"
  },
  {
    "name": "ATL-PHYS-PUB-2022-044",
    "url": "https://cds.cern.ch/record/2827111",
    "summary": "Search for heavy long-lived multi-charged particles in the full Run-II $pp$ collision data at $\\sqrt{s}$ = 13 TeV using the ATLAS detector",
    "releaseDate": "2022"
  },  {
    "name": "JHEP01(2018)055",
    "url": "https://doi.org/10.1007/JHEP01(2018)055",
    "publisher": "J. High Energ. Phys. 2018, 55 (2018).",
    "summary": "Search for additional heavy neutral Higgs and gauge bosons in the ditau final state produced in 36 fb1 of pp collisions at √s = 13 TeV with the ATLAS detector.",
    "releaseDate": "2018"
  }
    
],  

"references": [
    {
      "reference": "Professor Sinead Farrington",
      "name": "Research Primary Investigator, University of Edinburgh",
      "url": "https://www.ph.ed.ac.uk/people/sinead-farrington",
      "contact": "sinead.farrington@ed.ac.uk"
    },
    {
      "reference": "Dr Trevor Vickey",
      "name": "PhD Supervisor, University of Sheffield",
      "url": "https://www.sheffield.ac.uk/physics/people/academic/trevor-vickey",
      "contact": "t.vickey@sheffield.ac.uk"
    },
    {
      "reference": "Dr Nikolaos Rompotis",
      "name": "Work Colleague, University of Liverpool",
      "url": "https://www.liverpool.ac.uk/physics/staff/nikolaos-rompotis/",
      "contact": "Nikolaos.Rompotis@liverpool.ac.uk"
    }
    
  ],
  "skills": [
    {
	"keywords": ["Python", "Tensorflow", "Scipy", "Keras", "Pandas", "Numpy", "Jupyter", "matplotlib","valgrind", "CMake", "Unit Tests"],
      "level": "",
      "name": "Python/C++"
    },
    {
      "keywords": ["valgrind", "CMake", "Unit Tests"],
      "level": "",
      "name": "C++"
    },
    {
	"keywords": ["Hypothesis testing","Likelihood Models", "A/B tests", "SQL"],
      "level": "",
      "name": "Statistics"
    },
    {
	"keywords": ["Feature extraction", "BDTs", "Random Forests", "Neural Networks", "Autoencoders", "GANS"],
      "level": "",
      "name": "Machine Learning"
    },
    {
	"keywords": ["AWS","SQL", "Git-CI", "Docker", "Kubernetes", "Linux/Server" ,"MongoDB"],
      "level": "",
      "name": "Technology"
    },
    {
	"keywords": ["VC", "Git-CI", "Docker", "Kubernetes","Linux/Server", "Distributed Computing","IaC (Terraform)"],
      "level": "",
      "name": "Tech"
    },
    {
	"keywords": ["Raspberry-pi", "Electronics", "Machine Code", "Soldering", "HTML", "CSS", "Apache", "SQL", "Tor", "OnionShare"],
      "level": "Hobbyist",
      "name": "Hobbies"
    },
    {
      "keywords": ["HTML", "CSS", "Apache", "SQL", "Tor", "OnionShare"],
      "level": "Hobbyist",
      "name": "WebDev"
    },
    {
	"keywords": ["Git", "Git-CI", "Docker", "IaC (Terraform)", "YAML", "JSON", "Kubernetes"],
      "level": "",
      "name": "Dev"
    }    
  ],
  "work": [
    {
      "summary": "\\textbf{Leading researcher} in analysis group at CERN, searching for new physics. Active in precision measurements with model interpretation. Focus on data-driven estimations.",
      "name": "Postdoctoral Research Associate",
      "location": "The University of Edinburgh",
      "position": "Research",
      "startDate": "2019",
      "endDate": "May 2023",
      "highlights": [
	  "Active in the development of all areas of physics \\textbf{analysis}, incl.\\linebreak data preparation, software development/maintenance, algorithm design/deployment, and statistical intepretation.",
	  "Active in the development of all areas of physics \\textbf{analysis}, incl.\\linebreak data preparation, software infrastructure development and maintenance, algorithm design and deployment, and statistical intepretation.}",
          "\\textbf{Developed software} for particle tracking and identification in particle reconstruction and triggering. \\textbf{Deployed software} in collaboration software release.",
          "Delivered software algorithms using \\textbf{neural-networks} for particle identification, as well as \\textbf{develop c++/python} analysis tools with \\textbf{widespread use in the collaboration}.",
        "Have been an \\textbf{analysis leader}, involved in ongoing publications, including technical reports. Experienced in paper writing and peer-review in \\textbf{leading journals}. Present at international conferences.",
          "Convened over research team in \\textbf{group meetings} with regular interaction and group work. Am resposible for \\textbf{teaching and supervision} of several PhD students on analysis and tasks within the working group."
        
      ]
    },
    {
      "name": "Lecturing",
      "summary": "Lecture Honours level Machine Learning module. Course covers topics from linear regression and decision trees, to adversarial neural networks. Deliver practical computing labs and an end year project on machine learning conducted in Python. Additionally, provide supervision for an Honours student project on particle identification.",
      "location": "The University of Edinburgh",
      "position": "Machine Learning Lectures",
      "startDate": "2021-09-01",
      "highlights": [        
        "\\textbf{Deliver lectures} and workshops on \\textbf{machine learning} with an emphasis on applicability in the field of particle physics. Four week course covering \\textbf{data preparation}, \\textbf{regression} and \\textbf{classification decision trees}, \\textbf{feature extraction}, and \\textbf{neural-networs} (\\emph{DNNs, RNNs, CNNs, VAEs, GANs})",
        "Designed MSc machine learning project using novel techniques in ML and image processing in physics. Oversee supervision and marking, and supervised honours student projects.",
        "Supervised honours student on particle identification project using boosted decision trees"
      ]
    },
    {
      "name":"PhD research",
      "summary":"PhD student researching Exotic Higgs physics with major contribtuions to three leading publications.",
      "location":"The University of Sheffield",
      "position": "PhD candidate",
      "startDate":"2015",
      "endDate":"2019",
      "highlights": ["Performed statstical analysis of Higgs and charged Higgs publications. Developed code and workfolow for statistical interpretation and interpretation of the analysis results. ",
        "Conducted statistical interpretation of the Higgs precision measurement in the context of exotic physics models.",
        "Worked within common performance groups to deliver on early 2016 performance results.",
        "Worked on the construction and testing of silicon particle detectors for the ATLAS upgrade.",
        "Attended several schools on computing, machine learning, and particle physics. Teaching Assistant for several mathematics, physics and programming courses. Presented at international conferences."
      ]
    } 
  ]
}
